sage_setup/__init__.py
sage_setup/cython_options.py
sage_setup/excepthook.py
sage_setup/extensions.py
sage_setup/find.py
sage_setup/library_order.py
sage_setup/run_parallel.py
sage_setup/setenv.py
sage_setup/util.py
sage_setup/autogen/__init__.py
sage_setup/autogen/__main__.py
sage_setup/autogen/flint_autogen.py
sage_setup/autogen/interpreters/__main__.py
sage_setup/autogen/interpreters/internal/__init__.py
sage_setup/autogen/interpreters/internal/generator.py
sage_setup/autogen/interpreters/internal/instructions.py
sage_setup/autogen/interpreters/internal/memory.py
sage_setup/autogen/interpreters/internal/storage.py
sage_setup/autogen/interpreters/internal/utils.py
sage_setup/autogen/interpreters/internal/specs/__init__.py
sage_setup/autogen/interpreters/internal/specs/base.py
sage_setup/autogen/interpreters/internal/specs/cc.py
sage_setup/autogen/interpreters/internal/specs/cdf.py
sage_setup/autogen/interpreters/internal/specs/element.py
sage_setup/autogen/interpreters/internal/specs/python.py
sage_setup/autogen/interpreters/internal/specs/rdf.py
sage_setup/autogen/interpreters/internal/specs/rr.py
sage_setup/command/__init__.py
sage_setup/command/sage_build_cython.py
sage_setup/command/sage_build_ext.py
sage_setup/command/sage_build_ext_minimal.py
sage_setup/command/sage_build_py.py
sage_setup/command/sage_install.py
sage_setup-10.7.dist-info/METADATA
sage_setup-10.7.dist-info/WHEEL
sage_setup-10.7.dist-info/top_level.txt
sage_setup-10.7.dist-info/RECORD
