Metadata-Version: 2.1
Name: sage-setup
Version: 10.7
Summary: Sage: Open Source Mathematics Software: Build system of the Sage library
Author-email: The Sage Developers <sage-support@googlegroups.com>
License: GNU General Public License (GPL) v2 or later
Project-URL: Homepage, https://www.sagemath.org
Classifier: Development Status :: 6 - Mature
Classifier: Intended Audience :: Education
Classifier: Intended Audience :: Science/Research
Classifier: License :: OSI Approved :: GNU General Public License v2 or later (GPLv2+)
Classifier: Operating System :: POSIX
Classifier: Operating System :: MacOS :: MacOS X
Classifier: Programming Language :: Python :: 3 :: Only
Classifier: Programming Language :: Python :: 3.9
Classifier: Programming Language :: Python :: 3.10
Classifier: Programming Language :: Python :: 3.11
Classifier: Programming Language :: Python :: 3.12
Classifier: Programming Language :: Python :: Implementation :: CPython
Classifier: Topic :: Scientific/Engineering :: Mathematics
Requires-Python: <3.14,>=3.9
Provides-Extra: autogen
Requires-Dist: jinja2 ; extra == 'autogen'
